evpy_/GUI3.py
evpy_/evpy.py
evpy_/interpolation.py
evpy-1.1.0.dist-info/LICENSE.txt
evpy-1.1.0.dist-info/METADATA
evpy-1.1.0.dist-info/WHEEL
evpy-1.1.0.dist-info/entry_points.txt
evpy-1.1.0.dist-info/top_level.txt
evpy-1.1.0.dist-info/RECORD
