Metadata-Version: 2.1
Name: evpy
Version: 1.1.0
Summary: A python package modeling electric power train components.
Home-page: UNKNOWN
Author: Dalton Chancellor
Author-email: UNKNOWN
License: MIT
Platform: UNKNOWN
Requires-Dist: numpy
Requires-Dist: scipy
